memfault_cli/__init__.py
memfault_cli/_version.py
memfault_cli/authenticator.py
memfault_cli/chunk.py
memfault_cli/cli.py
memfault_cli/console.py
memfault_cli/context.py
memfault_cli/deploy.py
memfault_cli/elf.py
memfault_cli/functools_ext.py
memfault_cli/linux.py
memfault_cli/upload.py
memfault_cli-1.7.1.dist-info/licenses/LICENSE
memfault_cli-1.7.1.dist-info/METADATA
memfault_cli-1.7.1.dist-info/WHEEL
memfault_cli-1.7.1.dist-info/entry_points.txt
memfault_cli-1.7.1.dist-info/top_level.txt
memfault_cli-1.7.1.dist-info/RECORD
