Metadata-Version: 2.4
Name: memfault-cli
Version: 1.7.1
Summary: Memfault CLI tool
Author-email: Memfault <hello@memfault.com>
License:                                  Apache License
Project-URL: homepage, https://docs.memfault.com
Project-URL: documentation, https://docs.memfault.com/docs/cli
Requires-Python: <4.0,>=3.9
License-File: LICENSE
Requires-Dist: Click<9,>=7
Requires-Dist: requests<3.0.0,>=2.32.4
Requires-Dist: pyelftools>=0.31
Requires-Dist: mflt-build-id<2.0.0,>=1.0.2
Requires-Dist: more-itertools>=8.0.2
Requires-Dist: pyaxmlparser<0.4.0,>=0.3.24
Requires-Dist: tqdm<5.0.0,>=4.67.1
Requires-Dist: urllib3<3.0.0,>=2.6.3
Requires-Dist: pyserial<4.0,>=3.5
Dynamic: license-file
